patents_analysis_CN/__init__.py
patents_analysis_CN/patent_manager.py
patents_analysis_CN-1.0.0.dist-info/LICENSE
patents_analysis_CN-1.0.0.dist-info/METADATA
patents_analysis_CN-1.0.0.dist-info/WHEEL
patents_analysis_CN-1.0.0.dist-info/top_level.txt
patents_analysis_CN-1.0.0.dist-info/RECORD
