Metadata-Version: 2.1
Name: patents-analysis-CN
Version: 1.0.0
Summary: patents's analysis tools
Home-page: https://github.com/acompe/patents_tools
Author: acompe
Author-email: acompe@qq.com
License-File: LICENSE
